tencent_bkbase_datalake/__init__.py
tencent_bkbase_datalake/tables.py
tencent_bkbase_datalake/lib/datalake-sdk-4.0.1-with-dependencies.jar
tencent_bkbase_datalake-4.0.1.dist-info/LICENSE
tencent_bkbase_datalake-4.0.1.dist-info/METADATA
tencent_bkbase_datalake-4.0.1.dist-info/WHEEL
tencent_bkbase_datalake-4.0.1.dist-info/top_level.txt
tencent_bkbase_datalake-4.0.1.dist-info/RECORD
